{"version":3,"commands":{"hotkey-translate-page-1":{"precedenceList":[{"id":"{036a55b4-5e72-4d05-a06c-cba2dfcc134a}","installDate":1735926119576,"value":{"shortcut":"Ctrl+1"},"enabled":true}]},"hotkey-translate-page-2":{"precedenceList":[{"id":"{036a55b4-5e72-4d05-a06c-cba2dfcc134a}","installDate":1735926119576,"value":{"shortcut":"Ctrl+2"},"enabled":true}]}},"url_overrides":{},"prefs":{"network.networkPredictionEnabled":{"initialValue":{},"precedenceList":[{"id":"jid1-MnnxcxisBPnSXQ@jetpack","installDate":1737468090216,"value":false,"enabled":true}]},"websites.hyperlinkAuditingEnabled":{"initialValue":{},"precedenceList":[{"id":"jid1-MnnxcxisBPnSXQ@jetpack","installDate":1737468090216,"value":false,"enabled":true}]}}}